[
    {
        "id": 1,
        "title": "To Kill a Mockingbird",
        "author": "Harper Lee",
        "description": "A powerful coming-of-age novel set in the American South, exploring justice, prejudice, courage, and moral growth through the eyes of young Scout Finch.",
        "category": "Fiction",
        "available_quantity": 12,
        "image_url": "https://covers.openlibrary.org/b/isbn/9780061120084-L.jpg"
    },
    {
        "id": 2,
        "title": "1984",
        "author": "George Orwell",
        "description": "A dystopian novel about surveillance, propaganda, thought control, and one man's struggle against a totalitarian regime.",
        "category": "Fiction",
        "available_quantity": 9,
        "image_url": "https://covers.openlibrary.org/b/isbn/9780451524935-L.jpg"
    },
    {
        "id": 3,
        "title": "The Great Gatsby",
        "author": "F. Scott Fitzgerald",
        "description": "A Jazz Age classic about wealth, obsession, illusion, and the fragile dream surrounding Jay Gatsby and Daisy Buchanan.",
        "category": "Fiction",
        "available_quantity": 15,
        "image_url": "https://covers.openlibrary.org/b/isbn/9780743273565-L.jpg"
    },
    {
        "id": 4,
        "title": "Pride and Prejudice",
        "author": "Jane Austen",
        "description": "A witty romantic classic following Elizabeth Bennet as she navigates love, family pressure, class expectations, and first impressions.",
        "category": "Romance",
        "available_quantity": 18,
        "image_url": "https://covers.openlibrary.org/b/isbn/9780141439518-L.jpg"
    },
    {
        "id": 5,
        "title": "The Catcher in the Rye",
        "author": "J. D. Salinger",
        "description": "A landmark coming-of-age novel following Holden Caulfield as he wanders New York City and wrestles with alienation, grief, and adulthood.",
        "category": "Adventure",
        "available_quantity": 7,
        "image_url": "https://covers.openlibrary.org/b/isbn/9780316769488-L.jpg"
    },
    {
        "id": 6,
        "title": "The Hobbit",
        "author": "J. R. R. Tolkien",
        "description": "Bilbo Baggins leaves his comfortable home for a grand adventure with dwarves, trolls, goblins, riddles, treasure, and a dragon named Smaug.",
        "category": "Fantasy",
        "available_quantity": 14,
        "image_url": "https://covers.openlibrary.org/b/isbn/9780547928227-L.jpg"
    },
    {
        "id": 7,
        "title": "Fahrenheit 451",
        "author": "Ray Bradbury",
        "description": "A dystopian story about a future society where books are banned and burned, following fireman Guy Montag as he begins to question everything.",
        "category": "Fiction",
        "available_quantity": 10,
        "image_url": "https://covers.openlibrary.org/b/isbn/9781451673319-L.jpg"
    },
    {
        "id": 8,
        "title": "Moby-Dick",
        "author": "Herman Melville",
        "description": "An epic sea voyage led by Captain Ahab, whose obsessive hunt for the white whale becomes a meditation on fate, revenge, and human ambition.",
        "category": "Adventure",
        "available_quantity": 6,
        "image_url": "https://covers.openlibrary.org/b/isbn/9780142437247-L.jpg"
    },
    {
        "id": 9,
        "title": "The Alchemist",
        "author": "Paulo Coelho",
        "description": "A philosophical tale about Santiago, a shepherd boy who follows a dream across the desert in search of treasure and personal destiny.",
        "category": "Fantasy",
        "available_quantity": 20,
        "image_url": "https://covers.openlibrary.org/b/isbn/9780061122415-L.jpg"
    },
    {
        "id": 10,
        "title": "The Book Thief",
        "author": "Markus Zusak",
        "description": "Set in Nazi Germany, this moving novel follows Liesel Meminger, a young girl who finds comfort and resistance through stolen books and words.",
        "category": "Adventure",
        "available_quantity": 11,
        "image_url": "https://covers.openlibrary.org/b/isbn/9780375842207-L.jpg"
    },
    {
        "id": 11,
        "title": "The Kite Runner",
        "author": "Khaled Hosseini",
        "description": "A deeply emotional story of friendship, betrayal, guilt, and redemption set against decades of Afghan history.",
        "category": "Fantasy",
        "available_quantity": 8,
        "image_url": "https://covers.openlibrary.org/b/isbn/9781594631931-L.jpg"
    },
    {
        "id": 12,
        "title": "The Road",
        "author": "Cormac McCarthy",
        "description": "A bleak yet tender post-apocalyptic novel about a father and son traveling through a ruined world while trying to preserve hope and humanity.",
        "category": "Fiction",
        "available_quantity": 5,
        "image_url": "https://covers.openlibrary.org/b/isbn/9780307387899-L.jpg"
    },
    {
        "id": 13,
        "title": "The Hunger Games",
        "author": "Suzanne Collins",
        "description": "Katniss Everdeen is forced into a televised fight for survival in Panem, a brutal nation ruled by spectacle, fear, and rebellion.",
        "category": "Adventure",
        "available_quantity": 16,
        "image_url": "https://covers.openlibrary.org/b/isbn/9780439023481-L.jpg"
    },
    {
        "id": 14,
        "title": "Harry Potter and the Sorcerer's Stone",
        "author": "J. K. Rowling",
        "description": "Harry Potter discovers he is a wizard and begins his first year at Hogwarts, where friendship, magic, danger, and mystery await.",
        "category": "Fantasy",
        "available_quantity": 13,
        "image_url": "https://covers.openlibrary.org/b/isbn/9780590353427-L.jpg"
    }
]